GUESSmyLT/GUESSmyLT.py
GUESSmyLT/Snakefile
GUESSmyLT/__init__.py
GUESSmyLT/bowtie2
GUESSmyLT/busco
GUESSmyLT/check_programs
GUESSmyLT/inferr
GUESSmyLT/inferr_lib.py
GUESSmyLT/samtools
GUESSmyLT/subsample
GUESSmyLT/trinity
GUESSmyLT/data/bacteria_odb9.tar.gz
GUESSmyLT/data/eukaryota_odb9.tar.gz
GUESSmyLT/test/4.fa
GUESSmyLT/test/4_r1.fastq.gz
GUESSmyLT/test/4_r2.fastq.gz
GUESSmyLT/test/__init__.py
GUESSmyLT/test/example.py
guessmylt-0.2.5.dist-info/LICENSE
guessmylt-0.2.5.dist-info/METADATA
guessmylt-0.2.5.dist-info/WHEEL
guessmylt-0.2.5.dist-info/entry_points.txt
guessmylt-0.2.5.dist-info/top_level.txt
guessmylt-0.2.5.dist-info/RECORD
