Metadata-Version: 2.1
Name: guessmylt
Version: 0.2.5
Summary: An efficient way to guess the library type of RNA-reads
Home-page: https://github.com/NBISweden/GUESSmyLT
Author: Hampus Olin, Erik Berner-Wik, Caitlin Vigetun Haughey, Lisa Klasson, Jacques Dainat
Author-email: UNKNOWN
License: GPL-3.0
Platform: UNKNOWN
Requires-Dist: biopython (==1.67)
Requires-Dist: bcbio-gff (==0.6.4)
Requires-Dist: pysam (>=0.13.0)
Requires-Dist: snakemake (==5.4.*)
